jinja2_ext_path/__init__.py
jinja2_ext_path/path_extension.py
jinja2_ext_path-0.2.0.dist-info/METADATA
jinja2_ext_path-0.2.0.dist-info/WHEEL
jinja2_ext_path-0.2.0.dist-info/RECORD
